{
  "driverVersions": ["10.2.3", "11.2.3", "12.4.2"],
  "endpoints": [
    {
      "server": "4.245.92.227",
	  "port": 1433
      "databaseName": "company",
      "user": "sa",
      "password": "Password123",
      "config": {
        "applicationIntent": ["ReadOnly", "ReadWrite"],
        "useEncryption": [false],
        "trustServerCertificate": [true],
        "multipleActiveResultSets": [false],
        "transparentNetworkIPResolution": [true, false],
        "autoCommit": [false],
        "useUnicode": [true],
        "isolationLevels": [1, 2]
      }
    },
    {
	  "server": "20.56.242.157",
      "port": 1433,
      "databaseName": "company",
      "user": "sa",
      "password": "Password123",
      "config": {
        "applicationIntent": ["ReadWrite"],
        "useEncryption": [true],
        "trustServerCertificate": [true],
        "multipleActiveResultSets": [true, false],
        "transparentNetworkIPResolution": [true, false],
        "autoCommit": [false],
        "useUnicode": [true],
        "isolationLevels": [4, 8]
      }
	}
  ]
}
